unophysics/_LADCGUI.py
unophysics/__init__.py
unophysics/_config.py
unophysics/_ladc.py
unophysics/_nbtools.py
unophysics/_quantum.py
unophysics/_wavefuncs.py
unophysics/cli.py
unophysics/config.py
unophysics/ladc.py
unophysics/nbtools.py
unophysics/quantum.py
unophysics/wavefuncs.py
unophysics-0.5.4.dist-info/AUTHORS.md
unophysics-0.5.4.dist-info/LICENSE
unophysics-0.5.4.dist-info/METADATA
unophysics-0.5.4.dist-info/WHEEL
unophysics-0.5.4.dist-info/entry_points.txt
unophysics-0.5.4.dist-info/top_level.txt
unophysics-0.5.4.dist-info/RECORD
