Metadata-Version: 2.1
Name: unophysics
Version: 0.5.4
Summary: Tools for physics from UNO.
Home-page: https://github.com/micha2718l/unophysics
Author: Michael Haas
Author-email: mjhaas@uno.edu
License: MIT license
Keywords: unophysics
Platform: UNKNOWN
Classifier: Development Status :: 2 - Pre-Alpha
Classifier: Intended Audience :: Developers
Classifier: License :: OSI Approved :: MIT License
Classifier: Natural Language :: English
Classifier: Programming Language :: Python :: 3
Classifier: Programming Language :: Python :: 3.6
Classifier: Programming Language :: Python :: 3.7
Requires-Dist: Click (>=6.0)
Requires-Dist: requests
Requires-Dist: sshtunnel
Requires-Dist: pymongo
Requires-Dist: sympy
Requires-Dist: jupyter
Requires-Dist: numpy
Requires-Dist: matplotlib
Requires-Dist: scipy
Requires-Dist: PyWavelets
Requires-Dist: pandas
